CODA/Alignment.py
CODA/Common_domain.py
CODA/Cross_correlation.py
CODA/Preprocessing.py
CODA/RGBgenerator.py
CODA/__init__.py
CODA/utils.py
icoda-1.0.0.dist-info/licenses/LICENSE
icoda-1.0.0.dist-info/METADATA
icoda-1.0.0.dist-info/WHEEL
icoda-1.0.0.dist-info/top_level.txt
icoda-1.0.0.dist-info/RECORD
