Metadata-Version: 2.4
Name: icoda
Version: 1.0.0
Summary: Integrative cross-sample alignment and spatially differential gene analysis for spatial transcriptomics
Home-page: https://github.com/xiaojierzi/CODA
Author: Yecheng Tan
Author-email: yctan21@m.fudan.edu.cn
License: GNU General Public License v3.0
Requires-Python: >=3.9
License-File: LICENSE
Dynamic: author
Dynamic: author-email
Dynamic: home-page
Dynamic: license
Dynamic: license-file
Dynamic: requires-python
Dynamic: summary
